<annotation>
	<folder>field_02_12_2020_filtered</folder>
	<filename>3dsense_2020_12_2_19_51_19_burst_31_color.jpg</filename>
	<path>/mnt/veracrypt1/3dsense/field_02_12_2020_filtered/3dsense_2020_12_2_19_51_19_burst_31_color.jpg</path>
	<source>
		<database>Unknown</database>
	</source>
	<size>
		<width>672</width>
		<height>376</height>
		<depth>3</depth>
	</size>
	<segmented>0</segmented>
	<object>
		<name>robot</name>
		<pose>Unspecified</pose>
		<truncated>0</truncated>
		<difficult>0</difficult>
		<bndbox>
			<xmin>354</xmin>
			<ymin>128</ymin>
			<xmax>425</xmax>
			<ymax>249</ymax>
		</bndbox>
	</object>
	<object>
		<name>human</name>
		<pose>Unspecified</pose>
		<truncated>0</truncated>
		<difficult>0</difficult>
		<bndbox>
			<xmin>100</xmin>
			<ymin>16</ymin>
			<xmax>244</xmax>
			<ymax>247</ymax>
		</bndbox>
	</object>
	<object>
		<name>human</name>
		<pose>Unspecified</pose>
		<truncated>0</truncated>
		<difficult>0</difficult>
		<bndbox>
			<xmin>301</xmin>
			<ymin>102</ymin>
			<xmax>346</xmax>
			<ymax>201</ymax>
		</bndbox>
	</object>
</annotation>
